README.txt
rstyoutube.py
setup.py
bin/rst2html+youtube.py
rstyoutube.egg-info/PKG-INFO
rstyoutube.egg-info/SOURCES.txt
rstyoutube.egg-info/dependency_links.txt
rstyoutube.egg-info/requires.txt
rstyoutube.egg-info/top_level.txt