Metadata-Version: 1.0
Name: rstyoutube
Version: 0.1
Summary: A directive to embed youtube videos in reStructuredText documents
Home-page: http://bitbucket.org/cliff/rstyoutube
Author: J. Cliff Dyer
Author-email: jcd@sdf.lonestar.org
License: LICENSE.txt
Platform: UNKNOWN
Classifier: Development Status :: 3 - Alpha
Classifier: Intended Audience :: Developers
Classifier: License :: OSI Approved :: MIT License
Classifier: Operating System :: OS Independent
Classifier: Programming Language :: Python
Classifier: Programming Language :: Python :: 2
Classifier: Topic :: Documentation
